vax/__init__.py
vax/cvs.py
vax/riteaid.py
vax/scan.py
vax/walgreens.py
vax-0.0.4.dist-info/LICENSE
vax-0.0.4.dist-info/METADATA
vax-0.0.4.dist-info/WHEEL
vax-0.0.4.dist-info/top_level.txt
vax-0.0.4.dist-info/RECORD
