Metadata-Version: 2.1
Name: vax
Version: 0.0.4
Summary: Finding covid vaccine appointment slots
Home-page: https://github.com/thorwhalen/vax/
License: mit
Platform: any
Requires-Dist: requests
